cornucopia/__init__.py
cornucopia/_version.py
cornucopia/base.py
cornucopia/baseutils.py
cornucopia/contrast.py
cornucopia/ctx.py
cornucopia/fov.py
cornucopia/geometric.py
cornucopia/intensity.py
cornucopia/io.py
cornucopia/kspace.py
cornucopia/labels.py
cornucopia/noise.py
cornucopia/psf.py
cornucopia/qmri.py
cornucopia/random.py
cornucopia/special.py
cornucopia/synth.py
cornucopia/tests/__init__.py
cornucopia/tests/test_run_contrast.py
cornucopia/tests/test_run_fov.py
cornucopia/tests/test_run_geometric.py
cornucopia/tests/test_run_intensity.py
cornucopia/tests/test_run_kspace.py
cornucopia/tests/test_run_labels.py
cornucopia/tests/test_run_noise.py
cornucopia/tests/test_run_psf.py
cornucopia/tests/test_run_qmri.py
cornucopia/tests/test_run_synth.py
cornucopia/utils/__init__.py
cornucopia/utils/b0.py
cornucopia/utils/bounds.py
cornucopia/utils/conv.py
cornucopia/utils/gmm.py
cornucopia/utils/indexing.py
cornucopia/utils/io.py
cornucopia/utils/jit.py
cornucopia/utils/kernels.py
cornucopia/utils/morpho.py
cornucopia/utils/padding.py
cornucopia/utils/patch.py
cornucopia/utils/py.py
cornucopia/utils/version.py
cornucopia/utils/warps.py
cornucopia-0.3.0.dist-info/LICENSE
cornucopia-0.3.0.dist-info/METADATA
cornucopia-0.3.0.dist-info/WHEEL
cornucopia-0.3.0.dist-info/top_level.txt
cornucopia-0.3.0.dist-info/RECORD
