Metadata-Version: 2.1
Name: cornucopia
Version: 0.3.0
Summary: An abundance of augmentation layers
Home-page: UNKNOWN
Author: Yael Balbastre
Author-email: yael.balbastre@gmail.com
License: MIT
Project-URL: Source Code, https://github.com/balbasty/cornucopia
Platform: OS Independent
Classifier: License :: OSI Approved :: MIT License
Classifier: Operating System :: OS Independent
Classifier: Programming Language :: Python :: 3
Classifier: Intended Audience :: Science/Research
Classifier: Topic :: Scientific/Engineering :: Artificial Intelligence
Classifier: Topic :: Scientific/Engineering :: Medical Science Apps.
Requires-Python: >=3.6
Requires-Dist: torch >=1.8
Requires-Dist: numpy
Requires-Dist: nibabel
Requires-Dist: torch-interpol >=0.2.4
Requires-Dist: torch-distmap
